django_s3_express_cache/__init__.py
django_s3_express_cache/decorators.py
django_s3_express_cache/middleware.py
django_s3_express_cache-0.2.0.dist-info/licenses/LICENSE
django_s3_express_cache-0.2.0.dist-info/METADATA
django_s3_express_cache-0.2.0.dist-info/WHEEL
django_s3_express_cache-0.2.0.dist-info/top_level.txt
django_s3_express_cache-0.2.0.dist-info/RECORD
