Metadata-Version: 2.4
Name: django-s3-express-cache
Version: 0.2.0
Summary: django-s3-express-cache
Author-email: Free Law Project <info@free.law>
License-Expression: BSD-2-Clause
Project-URL: Repository, https://github.com/freelawproject/django-s3-express-cache
Project-URL: Organisation Homepage, https://free.law/
Keywords: legal,courts
Classifier: Development Status :: 5 - Production/Stable
Classifier: Intended Audience :: Developers
Classifier: Natural Language :: English
Classifier: Operating System :: OS Independent
Classifier: Programming Language :: Python
Classifier: Programming Language :: Python :: 3
Classifier: Programming Language :: Python :: 3.13
Classifier: Programming Language :: Python :: Implementation :: CPython
Classifier: Programming Language :: Python :: Implementation :: PyPy
Classifier: Topic :: Software Development :: Libraries :: Python Modules
Requires-Python: >=3.13
License-File: LICENSE
Requires-Dist: Django>=5.0
Requires-Dist: boto3>=1.37.20
Dynamic: license-file
